mizdb_tomselect/__init__.py
mizdb_tomselect/views.py
mizdb_tomselect/widgets.py
mizdb_tomselect/static/mizdb_tomselect/css/mizselect.css
mizdb_tomselect/static/mizdb_tomselect/js/mizselect.js
mizdb_tomselect/static/mizdb_tomselect/js/popup_response.js
mizdb_tomselect/static/vendor/tom-select/css/tom-select.bootstrap5.css
mizdb_tomselect/static/vendor/tom-select/css/tom-select.bootstrap5.css.map
mizdb_tomselect/templates/mizdb_tomselect/popup_response.html
mizdb_tomselect-0.11.0.dist-info/licenses/LICENSE
mizdb_tomselect-0.11.0.dist-info/METADATA
mizdb_tomselect-0.11.0.dist-info/WHEEL
mizdb_tomselect-0.11.0.dist-info/top_level.txt
mizdb_tomselect-0.11.0.dist-info/RECORD
