Metadata-Version: 2.4
Name: mizdb-tomselect
Version: 0.11.0
Summary: Django autocomplete widgets and views using TomSelect
Author-email: Philip Becker <yummytea1@gmail.com>
Project-URL: Source, https://github.com/Actionb/mizdb-tomselect
Classifier: Framework :: Django
Classifier: Programming Language :: Python :: 3
Requires-Python: >=3.9
License-File: LICENSE
Requires-Dist: Django
Dynamic: license-file
